geopack/__init__.py
geopack/geopack.py
geopack/t01.py
geopack/t04.py
geopack/t89.py
geopack/t96.py
geopack/test_geopack1.md
geopack/test_geopack1.py
geopack-1.0.12.dist-info/licenses/LICENSE
geopack-1.0.12.dist-info/METADATA
geopack-1.0.12.dist-info/WHEEL
geopack-1.0.12.dist-info/top_level.txt
geopack-1.0.12.dist-info/RECORD
