Metadata-Version: 2.4
Name: geopack
Version: 1.0.12
Summary: Python version of geopack and Tsyganenko models, compatible with geopack05 and geopack08
Home-page: https://github.com/tsssss/geopack
Author: Sheng Tian
Author-email: ts0110@atmos.ucla.edu
License: MIT
Keywords: geopack,space physics,Tsyganenko model
Platform: Mac OS
Classifier: Programming Language :: Python :: 3
Classifier: Operating System :: MacOS
Classifier: Development Status :: 3 - Alpha
Classifier: Intended Audience :: Science/Research
Classifier: License :: OSI Approved :: MIT License
Classifier: Topic :: Scientific/Engineering :: Physics
License-File: LICENSE
Requires-Dist: numpy
Requires-Dist: scipy
Dynamic: author
Dynamic: author-email
Dynamic: classifier
Dynamic: description
Dynamic: description-content-type
Dynamic: home-page
Dynamic: keywords
Dynamic: license
Dynamic: license-file
Dynamic: platform
Dynamic: requires-dist
Dynamic: summary
